MANIFEST.in
README.rst
setup.py
quoteBot/__init__.py
quoteBot/__main__.py
quoteBot/quoteBot.py
quoteBot.egg-info/PKG-INFO
quoteBot.egg-info/SOURCES.txt
quoteBot.egg-info/dependency_links.txt
quoteBot.egg-info/entry_points.txt
quoteBot.egg-info/requires.txt
quoteBot.egg-info/top_level.txt
quoteBot/commands/__init__.py
quoteBot/commands/authenticate.py
quoteBot/commands/parser.py
quoteBot/commands/secrets.py