Metadata-Version: 1.0
Name: quoteBot
Version: 0.2.52.dev0
Summary: a package to create text quote bots on twitter quickly
Home-page: https://github.com/ejmg/quoteBot
Author: elias julian marko garcia
Author-email: elias.jm.garcia@gmail.com
License: MIT
Platform: UNKNOWN
